coverup/__init__.py
coverup/__main__.py
coverup/codeinfo.py
coverup/coverup.py
coverup/llm.py
coverup/logreader.py
coverup/segment.py
coverup/testrunner.py
coverup/utils.py
coverup/version.py
coverup/prompt/__init__.py
coverup/prompt/claude.py
coverup/prompt/gpt_v1.py
coverup/prompt/gpt_v2.py
coverup/prompt/gpt_v2_ablated.py
coverup/prompt/gpt_v2_fully_ablated.py
coverup/prompt/prompter.py
coverup-0.6.3.dist-info/licenses/LICENSE
coverup-0.6.3.dist-info/METADATA
coverup-0.6.3.dist-info/WHEEL
coverup-0.6.3.dist-info/entry_points.txt
coverup-0.6.3.dist-info/top_level.txt
coverup-0.6.3.dist-info/RECORD
