Metadata-Version: 2.4
Name: CoverUp
Version: 0.6.3
Summary: LLM-powered test coverage improver
Author-email: Juan Altmayer Pizzorno <juan@altmayer.com>, Emery Berger <emery.berger@gmail.com>
Project-URL: Homepage, https://github.com/plasma-umass/coverup
Project-URL: Repository, https://github.com/plasma-umass/coverup
Classifier: Programming Language :: Python :: 3.10
Classifier: Programming Language :: Python :: 3.11
Classifier: Programming Language :: Python :: 3.12
Classifier: Programming Language :: Python :: 3.13
Classifier: License :: OSI Approved :: Apache Software License
Classifier: Operating System :: POSIX :: Linux
Classifier: Operating System :: MacOS :: MacOS X
Requires-Python: >=3.10
License-File: LICENSE
Requires-Dist: asyncio
Requires-Dist: openai
Requires-Dist: tiktoken
Requires-Dist: aiolimiter
Requires-Dist: tqdm
Requires-Dist: slipcover>=1.0.13
Requires-Dist: pytest-cleanslate>=1.0.6
Requires-Dist: pytest-isolate
Requires-Dist: pytest-repeat
Requires-Dist: litellm>=1.33.1
Dynamic: description
Dynamic: description-content-type
Dynamic: license-file
